dsn_tornado/__init__.py
dsn_tornado/server.py
dsn_tornado/session/__init__.py
dsn_tornado/session/redis.py
dsn_tornado_wrapper/__init__.py
dsn_tornado_wrapper/server.py
dsn_tornado_wrapper/session/__init__.py
dsn_tornado_wrapper/session/redis.py
dsn_tornado_wrapper-1.0.5.dist-info/DESCRIPTION.rst
dsn_tornado_wrapper-1.0.5.dist-info/METADATA
dsn_tornado_wrapper-1.0.5.dist-info/RECORD
dsn_tornado_wrapper-1.0.5.dist-info/WHEEL
dsn_tornado_wrapper-1.0.5.dist-info/metadata.json
dsn_tornado_wrapper-1.0.5.dist-info/top_level.txt
